{
	"configurations" : 
	[
		{
			"directories" : 
			[
				{
					"build" : ".",
					"jsonFile" : "directory-.-Debug-d0094a50bb2071803777.json",
					"minimumCMakeVersion" : 
					{
						"string" : "3.24"
					},
					"projectIndex" : 0,
					"source" : ".",
					"targetIndexes" : 
					[
						0
					]
				}
			],
			"name" : "Debug",
			"projects" : 
			[
				{
					"directoryIndexes" : 
					[
						0
					],
					"name" : "Class_1_Patterns_",
					"targetIndexes" : 
					[
						0
					]
				}
			],
			"targets" : 
			[
				{
					"directoryIndex" : 0,
					"id" : "Class_1_Patterns_::@6890427a1f51a3e7e1df",
					"jsonFile" : "target-Class_1_Patterns_-Debug-0e03aede0fe544bc7dcb.json",
					"name" : "Class_1_Patterns_",
					"projectIndex" : 0
				}
			]
		}
	],
	"kind" : "codemodel",
	"paths" : 
	{
		"build" : "D:/DSA(Supreme)/Weeks-2(Basic Programming-2)/Class 1(Patterns)/cmake-build-debug",
		"source" : "D:/DSA(Supreme)/Weeks-2(Basic Programming-2)/Class 1(Patterns)"
	},
	"version" : 
	{
		"major" : 2,
		"minor" : 4
	}
}
